pygplates-1.0.0rc1.dist-info/RECORD
pygplates-1.0.0rc1.dist-info/WHEEL
pygplates-1.0.0rc1.dist-info/METADATA
pygplates-1.0.0rc1.dist-info/licenses/COPYING
pygplates/pygplates.so
pygplates/__init__.py
pygplates/proj_data/proj.db
pygplates/proj_data/nad83
pygplates/proj_data/CH
pygplates/proj_data/world
pygplates/proj_data/proj.ini
pygplates/proj_data/nad.lst
pygplates/proj_data/ITRF2000
pygplates/proj_data/ITRF2008
pygplates/proj_data/triangulation.schema.json
pygplates/proj_data/deformation_model.schema.json
pygplates/proj_data/nad27
pygplates/proj_data/projjson.schema.json
pygplates/proj_data/GL27
pygplates/proj_data/ITRF2014
pygplates/proj_data/other.extra
pygplates/.dylibs/libgmpxx.4.dylib
pygplates/.dylibs/libsqlite3.0.dylib
pygplates/.dylibs/libpcre2-16.0.dylib
pygplates/.dylibs/libminizip.1.dylib
pygplates/.dylibs/QtPrintSupport
pygplates/.dylibs/QtOpenGL
pygplates/.dylibs/libboost_chrono-mt.dylib
pygplates/.dylibs/libxml2.2.dylib
pygplates/.dylibs/QtNetwork
pygplates/.dylibs/libspatialite.8.dylib
pygplates/.dylibs/librttopo.1.dylib
pygplates/.dylibs/libgraphite2.3.2.1.dylib
pygplates/.dylibs/libboost_thread-mt.dylib
pygplates/.dylibs/libpcre2-8.0.dylib
pygplates/.dylibs/libgeos_c.1.18.2.dylib
pygplates/.dylibs/libbrunslienc-c.dylib
pygplates/.dylibs/QtSvg
pygplates/.dylibs/libidn2.0.dylib
pygplates/.dylibs/QtXml
pygplates/.dylibs/libqhull_r.8.0.2.dylib
pygplates/.dylibs/libglib-2.0.0.dylib
pygplates/.dylibs/libicuuc.74.2.dylib
pygplates/.dylibs/libboost_python312-mt.dylib
pygplates/.dylibs/libgeos.3.12.2.dylib
pygplates/.dylibs/libproj.25.9.4.1.dylib
pygplates/.dylibs/libaec.0.dylib
pygplates/.dylibs/libpng16.16.dylib
pygplates/.dylibs/liblz4.1.9.4.dylib
pygplates/.dylibs/libicudata.74.2.dylib
pygplates/.dylibs/libexpat.1.9.2.dylib
pygplates/.dylibs/libiconv.2.dylib
pygplates/.dylibs/libboost_system-mt.dylib
pygplates/.dylibs/libssl.3.dylib
pygplates/.dylibs/libdouble-conversion.3.3.0.dylib
pygplates/.dylibs/libbrunslidec-c.dylib
pygplates/.dylibs/qwt
pygplates/.dylibs/libbrotlidec.1.1.0.dylib
pygplates/.dylibs/libfreetype.6.dylib
