Metadata-Version: 2.1
Name: pygplates
Version: 1.0.0rc1
Summary: Python library for fine-grained access to GPlates functionality.
Keywords: pygplates,gplates,plate,tectonics
Author-Email: John Cannon <john.cannon@sydney.edu.au>
Maintainer-Email: John Cannon <john.cannon@sydney.edu.au>
License:   Note that the GPL (GNU GENERAL PUBLIC LICENSE) appearing below
